pycodetags/_TODO.py
pycodetags/__about__.py
pycodetags/__init__.py
pycodetags/__main__.py
pycodetags/aggregate.py
pycodetags/common_interfaces.py
pycodetags/exceptions.py
pycodetags/logging_config.py
pycodetags/plugin_manager.py
pycodetags/plugin_specs.py
pycodetags/pure_data_schema.py
pycodetags/py.typed
pycodetags/app_config/__init__.py
pycodetags/app_config/config.py
pycodetags/app_config/config_init.py
pycodetags/data_tags/__init__.py
pycodetags/data_tags/data_tags_classes.py
pycodetags/data_tags/data_tags_methods.py
pycodetags/data_tags/data_tags_parsers.py
pycodetags/data_tags/data_tags_schema.py
pycodetags/data_tags/meta_builder.py
pycodetags/folk_tags/__init__.py
pycodetags/folk_tags/folk_tags_parser.py
pycodetags/folk_tags/folk_tags_schema.py
pycodetags/python/__init__.py
pycodetags/python/collect.py
pycodetags/python/comment_finder.py
pycodetags/utils/__init__.py
pycodetags/utils/cache_utils.py
pycodetags/utils/dotenv.py
pycodetags/views/__init__.py
pycodetags/views/view_tools.py
pycodetags/views/views.py
pycodetags-0.6.0.dist-info/METADATA
pycodetags-0.6.0.dist-info/WHEEL
pycodetags-0.6.0.dist-info/entry_points.txt
pycodetags-0.6.0.dist-info/licenses/AUTHORS.md
pycodetags-0.6.0.dist-info/licenses/LICENSE
pycodetags-0.6.0.dist-info/RECORD
