Metadata-Version: 2.4
Name: pycodetags
Version: 0.6.0
Summary: TODOs in source code as a first class construct, follows PEP350
Project-URL: Repository, https://github.com/matthewdeanmartin/pycodetags
Project-URL: Documentation, https://pycodetags.readthedocs.io/en/latest/
Project-URL: Changelog, https://github.com/matthewdeanmartin/pycodetags/blob/main/CHANGELOG.md
Project-URL: homepage, https://github.com/matthewdeanmartin/pycodetags
Project-URL: issues, https://matthewdeanmartin.github.io/pycodetags/
Author-email: Matthew Martin <matthewdeanmartin@gmail.com>
License-Expression: MIT
License-File: AUTHORS.md
License-File: LICENSE
Keywords: FIXME,TODO,code-tag,code-tags,codetag,codetags,pep-350,pep350,pycodetags
Classifier: Development Status :: 4 - Beta
Classifier: Intended Audience :: Developers
Classifier: License :: OSI Approved :: MIT License
Classifier: Operating System :: OS Independent
Classifier: Programming Language :: Python
Classifier: Programming Language :: Python :: 3.7
Classifier: Programming Language :: Python :: 3.8
Classifier: Programming Language :: Python :: 3.9
Classifier: Programming Language :: Python :: 3.10
Classifier: Programming Language :: Python :: 3.11
Classifier: Programming Language :: Python :: 3.12
Classifier: Programming Language :: Python :: 3.13
Classifier: Programming Language :: Python :: 3.14
Requires-Python: >=3.7
Requires-Dist: ast-comments>=1.2.3; python_version >= '3.8'
Requires-Dist: importlib-resources; python_version < '3.9'
Requires-Dist: jmespath
Requires-Dist: pluggy
Requires-Dist: toml; python_version < '3.11'
Requires-Dist: typing-extensions; python_version < '3.8'
